openbb_deribit/__init__.py
openbb_deribit/models/__init__.py
openbb_deribit/models/futures_curve.py
openbb_deribit/models/futures_historical.py
openbb_deribit/models/futures_info.py
openbb_deribit/models/futures_instruments.py
openbb_deribit/models/options_chains.py
openbb_deribit/utils/__init__.py
openbb_deribit/utils/helpers.py
openbb_deribit-1.1.1.dist-info/METADATA
openbb_deribit-1.1.1.dist-info/WHEEL
openbb_deribit-1.1.1.dist-info/entry_points.txt
openbb_deribit-1.1.1.dist-info/RECORD
