Metadata-Version: 2.4
Name: openbb-deribit
Version: 1.1.1
Summary: Deribit is a crypto-native derivatives exchange.
License: AGPL-3.0-only
Author: OpenBB Team
Author-email: hello@openbb.co
Requires-Python: >=3.10,<3.14
Classifier: License :: OSI Approved :: GNU Affero General Public License v3
Classifier: Programming Language :: Python :: 3
Classifier: Programming Language :: Python :: 3.10
Classifier: Programming Language :: Python :: 3.11
Classifier: Programming Language :: Python :: 3.12
Classifier: Programming Language :: Python :: 3.13
Requires-Dist: async-lru (>=2.0.4,<3.0.0)
Requires-Dist: openbb-core (>=1.5.7,<2.0.0)
